Metadata-Version: 2.1
Name: dmp
Version: 2018.11.6
Summary: Repackaging of Google's Diff Match and Patch libraries. Offers robust algorithms to perform the operations required for synchronizing plain text.
Home-page: https://github.com/jreese/dmp
Author: Neil Fraser
Author-email: fraser@google.com
License: Apache
Platform: UNKNOWN
Classifier: Development Status :: 6 - Mature
Classifier: Intended Audience :: Developers
Classifier: License :: OSI Approved :: Apache Software License
Classifier: Programming Language :: Python :: 2
Classifier: Programming Language :: Python :: 2.7
Classifier: Programming Language :: Python :: 3
Classifier: Programming Language :: Python :: 3.4
Classifier: Programming Language :: Python :: 3.5
Classifier: Programming Language :: Python :: 3.6
Classifier: Programming Language :: Python :: 3.7
Classifier: Topic :: Software Development :: Libraries
Classifier: Topic :: Text Processing
